pybencher.py
pybencher-1.0.6.dist-info/LICENSE
pybencher-1.0.6.dist-info/METADATA
pybencher-1.0.6.dist-info/WHEEL
pybencher-1.0.6.dist-info/top_level.txt
pybencher-1.0.6.dist-info/RECORD
