Metadata-Version: 2.1
Name: pybencher
Version: 1.0.6
Summary: PyBencher is a Python benchmarking module for benchmarking several python functions at once. PyBencher supports tuneable benchmarking parameters as well as args and kwargs for function calls.
Author-email: Barnaby Gill <barnabasgill@gmail.com>
Project-URL: Homepage, https://github.com/BarnabasG/pybencher
Project-URL: Issues, https://github.com/BarnabasG/pybencher/issues
Classifier: Programming Language :: Python :: 3
Classifier: License :: OSI Approved :: MIT License
Classifier: Operating System :: OS Independent
Requires-Python: >=3.6
License-File: LICENSE
